{
 "actions": [],
 "autoname": "hash",
 "creation": "2022-11-26 12:32:31.887807",
 "doctype": "DocType",
 "editable_grid": 1,
 "engine": "InnoDB",
 "field_order": [
  "equipment",
  "operator",
  "column_break_3",
  "equipment_type",
  "operator_name",
  "section_break_31",
  "ignore_time",
  "km_reading_section",
  "uom",
  "schedule_working_hrs",
  "total_km",
  "column_break_12",
  "initial_km",
  "column_break_22",
  "final_km",
  "time_recordhours_section",
  "start_time",
  "ot_hr",
  "column_break_18",
  "end_time",
  "column_break_20",
  "total_hours",
  "downtime_reason_section",
  "downtime_reason",
  "column_break_24",
  "downtime_hrs",
  "section_break_26",
  "remarks"
 ],
 "fields": [
  {
   "fieldname": "equipment",
   "fieldtype": "Link",
   "in_list_view": 1,
   "label": "Equipment",
   "options": "Equipment",
   "reqd": 1
  },
  {
   "fetch_from": "equipment.equipment_type",
   "fieldname": "equipment_type",
   "fieldtype": "Link",
   "in_list_view": 1,
   "label": "Equipment Type",
   "options": "Equipment Type",
   "read_only": 1
  },
  {
   "fieldname": "operator",
   "fieldtype": "Link",
   "ignore_user_permissions": 1,
   "label": "Operator",
   "options": "Employee"
  },
  {
   "fetch_from": "operator.employee_name",
   "fieldname": "operator_name",
   "fieldtype": "Data",
   "label": "Operator Name",
   "read_only": 1
  },
  {
   "fieldname": "column_break_3",
   "fieldtype": "Column Break"
  },
  {
   "depends_on": "eval:doc.ignore_time == 0",
   "fieldname": "km_reading_section",
   "fieldtype": "Section Break",
   "label": "KM/Hr Reading"
  },
  {
   "fieldname": "initial_km",
   "fieldtype": "Float",
   "label": "Initial KM/Hr",
   "mandatory_depends_on": "eval:doc.ignore_time == 0"
  },
  {
   "fieldname": "column_break_12",
   "fieldtype": "Column Break"
  },
  {
   "fieldname": "total_km",
   "fieldtype": "Float",
   "in_list_view": 1,
   "label": "Total KM/Hr",
   "read_only": 1
  },
  {
   "depends_on": "eval:doc.ignore_time == 0",
   "fieldname": "time_recordhours_section",
   "fieldtype": "Section Break",
   "label": "Time Record(Hours)"
  },
  {
   "fieldname": "start_time",
   "fieldtype": "Datetime",
   "label": "Start Time",
   "mandatory_depends_on": "eval:doc.ignore_time == 0"
  },
  {
   "fieldname": "column_break_18",
   "fieldtype": "Column Break"
  },
  {
   "fieldname": "end_time",
   "fieldtype": "Datetime",
   "label": "End Time",
   "mandatory_depends_on": "eval:doc.ignore_time == 0"
  },
  {
   "fieldname": "column_break_20",
   "fieldtype": "Column Break"
  },
  {
   "fieldname": "total_hours",
   "fieldtype": "Float",
   "in_list_view": 1,
   "label": "Total Hours",
   "read_only": 1
  },
  {
   "fieldname": "downtime_reason_section",
   "fieldtype": "Section Break",
   "label": "Downtime Reason"
  },
  {
   "fieldname": "downtime_reason",
   "fieldtype": "Link",
   "label": "Downtime Reason",
   "options": "Downtime Reason"
  },
  {
   "fieldname": "column_break_24",
   "fieldtype": "Column Break"
  },
  {
   "depends_on": "eval:doc.downtime_reason",
   "fieldname": "downtime_hrs",
   "fieldtype": "Float",
   "in_list_view": 1,
   "label": "Downtime Hrs",
   "mandatory_depends_on": "eval:doc.downtime_reason"
  },
  {
   "fieldname": "section_break_26",
   "fieldtype": "Section Break"
  },
  {
   "fieldname": "remarks",
   "fieldtype": "Small Text",
   "label": "Remarks"
  },
  {
   "fieldname": "final_km",
   "fieldtype": "Float",
   "label": "Final KM/Hr",
   "mandatory_depends_on": "eval:doc.ignore_time == 0"
  },
  {
   "fieldname": "column_break_22",
   "fieldtype": "Column Break"
  },
  {
   "fieldname": "ot_hr",
   "fieldtype": "Float",
   "label": "OT Hr"
  },
  {
   "fieldname": "uom",
   "fieldtype": "Select",
   "label": "Reading UOM",
   "mandatory_depends_on": "eval:doc.ignore_time == 0",
   "options": "\nKM\nHour"
  },
  {
   "depends_on": "eval:doc.uom == \"Hour\"",
   "fieldname": "schedule_working_hrs",
   "fieldtype": "Float",
   "label": "Schedule Working Hrs"
  },
  {
   "fieldname": "section_break_31",
   "fieldtype": "Section Break"
  },
  {
   "default": "0",
   "description": "<b>Tick this only for recording multiple holes dug in same Shift</b>",
   "fieldname": "ignore_time",
   "fieldtype": "Check",
   "label": "Ignore Reading & Time"
  }
 ],
 "index_web_pages_for_search": 1,
 "istable": 1,
 "links": [],
 "modified": "2023-05-23 16:09:41.032818",
 "modified_by": "Administrator",
 "module": "Fleet Management",
 "name": "Fleet Engagement Item",
 "naming_rule": "Random",
 "owner": "Administrator",
 "permissions": [],
 "sort_field": "modified",
 "sort_order": "DESC",
 "states": []
}