{
 "actions": [],
 "creation": "2020-05-13 10:49:26.368003",
 "doctype": "DocType",
 "editable_grid": 1,
 "engine": "InnoDB",
 "field_order": [
  "bank_name",
  "amount"
 ],
 "fields": [
  {
   "fieldname": "bank_name",
   "fieldtype": "Link",
   "in_list_view": 1,
   "label": "Bank",
   "options": "Financial Institution",
   "read_only": 1
  },
  {
   "fieldname": "amount",
   "fieldtype": "Currency",
   "in_list_view": 1,
   "label": "Amount",
   "read_only": 1
  }
 ],
 "istable": 1,
 "links": [],
 "modified": "2023-04-27 17:08:48.061375",
 "modified_by": "Administrator",
 "module": "Accounts",
 "name": "Bank Payment Summary",
 "owner": "Administrator",
 "permissions": [],
 "quick_entry": 1,
 "sort_field": "modified",
 "sort_order": "DESC",
 "states": [],
 "track_changes": 1
}